setup.py
django_zipkin_http/__init__.py
django_zipkin_http/api.py
django_zipkin_http/constants.py
django_zipkin_http/data_store.py
django_zipkin_http/defaults.py
django_zipkin_http/id_generator.py
django_zipkin_http/middleware.py
django_zipkin_http/utils.py
django_zipkin_http/zipkin_data.py
django_zipkin_http/zipkin_http.py
django_zipkin_http.egg-info/PKG-INFO
django_zipkin_http.egg-info/SOURCES.txt
django_zipkin_http.egg-info/dependency_links.txt
django_zipkin_http.egg-info/top_level.txt
django_zipkin_http/span/__init__.py
django_zipkin_http/span/annotation.py
django_zipkin_http/span/binary_annotation.py
django_zipkin_http/span/constants.py
django_zipkin_http/span/endpoint.py
django_zipkin_http/span/span.py