Metadata-Version: 1.1
Name: django-zipkin-http
Version: 0.0.1
Summary: django-zipkin-http is a Django middleware and api refering to django-zipkin for recording and sending messages to Zipkin via HTTP protocol
Home-page: https://github.com/leongxf/django-zipkin-http
Author: Leon Guo
Author-email: 934214227@qq.com
License: UNKNOWN
Keywords: django zipkin middleware http
Platform: any
Classifier: Environment :: Web Environment
Classifier: Framework :: Django
Classifier: Intended Audience :: Developers
Classifier: License :: Freely Distributable
Classifier: Operating System :: OS Independent
Classifier: Programming Language :: Python
Classifier: Programming Language :: Python :: 2
Classifier: Programming Language :: Python :: 2.7
Classifier: Topic :: Software Development :: Libraries :: Application Frameworks
Classifier: Topic :: Software Development :: Libraries :: Python Modules
